mobiedantic/__init__.py
mobiedantic/generated.py
mobiedantic-0.3.0.dist-info/METADATA
mobiedantic-0.3.0.dist-info/WHEEL
mobiedantic-0.3.0.dist-info/licenses/LICENSE.txt
mobiedantic-0.3.0.dist-info/RECORD
