Metadata-Version: 2.3
Name: mobiedantic
Version: 0.3.0
Project-URL: Documentation, https://github.com/fmi-faim/mobiedantic#readme
Project-URL: Issues, https://github.com/fmi-faim/mobiedantic/issues
Project-URL: Source, https://github.com/fmi-faim/mobiedantic
Author-email: Jan Eglinger <jan.eglinger@fmi.ch>
License-Expression: BSD-3-Clause
License-File: LICENSE.txt
Classifier: Development Status :: 4 - Beta
Classifier: Programming Language :: Python
Classifier: Programming Language :: Python :: 3.8
Classifier: Programming Language :: Python :: 3.9
Classifier: Programming Language :: Python :: 3.10
Classifier: Programming Language :: Python :: 3.11
Classifier: Programming Language :: Python :: 3.12
Classifier: Programming Language :: Python :: Implementation :: CPython
Classifier: Programming Language :: Python :: Implementation :: PyPy
Requires-Python: >=3.8
Requires-Dist: pydantic
Provides-Extra: hatch
Requires-Dist: hatch-conda<0.6,>=0.5.2; extra == 'hatch'
